gtran/__init__.py
gtran/gtran.py
gtran-0.1.5.dist-info/LICENSE
gtran-0.1.5.dist-info/METADATA
gtran-0.1.5.dist-info/WHEEL
gtran-0.1.5.dist-info/top_level.txt
gtran-0.1.5.dist-info/RECORD
