Metadata-Version: 2.1
Name: gtran
Version: 0.1.5
Summary: A free and unlimited Google translator.
Home-page: https://github.com/NTT1906/Gtran
Author: NTT1906
Author-email: nttispay@gmail.com
License: MIT
Keywords: translate gtran gtrans Gtran
Platform: UNKNOWN
Classifier: Development Status :: 5 - Production/Stable
Classifier: Intended Audience :: Education
Classifier: Intended Audience :: End Users/Desktop
Classifier: Intended Audience :: Developers
Classifier: License :: OSI Approved :: MIT License
Classifier: Operating System :: OS Independent
Classifier: Programming Language :: Python :: 3.2
Classifier: Programming Language :: Python :: 2.5
Classifier: Programming Language :: Python :: 3.8
Classifier: Programming Language :: Python
Classifier: Topic :: Education
Requires-Python: >3.2.0
Requires-Dist: pycurl
Requires-Dist: urllib3
